{
  "maps": {
    "idOthers": {
      "label": "Others",
      "state": 1,
      "bkmrk": {}
    }
  },
  "portals": {
    "idOthers": {
      "label": "Others",
      "state": 1,
      "bkmrk": {
        "a": {
          "latlng": "45.574431,9.169448",
          "label": "Percorso del Lago e delle Ville"
        },
        "b": {
          "latlng": "45.574608,9.17024",
          "label": "Pino Domestico - Pinus Pinea L."
        },
        "c": {
          "latlng": "45.574727,9.170978",
          "label": "Campo da Basket - via San Michele del Carso"
        },
        "d": {
          "latlng": "45.575096,9.171609",
          "label": "Campo da calcio a 11 di Incirano"
        },
        "e": {
          "latlng": "45.575312,9.172078",
          "label": "Madonnina Dell'Oratorio San Luigi di Incirano"
        },
        "f": {
          "latlng": "45.575276,9.17285",
          "label": "Parco Grubri\u00c3\u00a0"
        },
        "g": {
          "latlng": "45.575374,9.173303",
          "label": "Infopoint Parco Toti"
        },
        "h": {
          "latlng": "45.575796,9.174054",
          "label": "Parco Grugnotorto Villoresi - Parco locale di interesse sovracomunale"
        },
        "i": {
          "latlng": "45.576114,9.174951",
          "label": "Bacheca Informativa - Parco Lago Nord"
        },
        "j": {
          "latlng": "45.576335,9.175507",
          "label": "Parco GruBr\u00c3\u00aca"
        }
      }
    }
  }
}